util_belt/__init__.py
util_belt/display_utils.py
util_belt/file_utils.py
util_belt-0.0.9.dist-info/LICENSE
util_belt-0.0.9.dist-info/METADATA
util_belt-0.0.9.dist-info/WHEEL
util_belt-0.0.9.dist-info/top_level.txt
util_belt-0.0.9.dist-info/RECORD
